babplay_mpd_playlist.py
babplay_randomly.py
babsearch_n_replace.py
babtools_misc.py
get_all_files.py
setup.py
babtools_misc.egg-info/PKG-INFO
babtools_misc.egg-info/SOURCES.txt
babtools_misc.egg-info/dependency_links.txt
babtools_misc.egg-info/top_level.txt